gg_commit.py
gg_commit-0.0.1.dist-info/DESCRIPTION.rst
gg_commit-0.0.1.dist-info/METADATA
gg_commit-0.0.1.dist-info/RECORD
gg_commit-0.0.1.dist-info/WHEEL
gg_commit-0.0.1.dist-info/entry_points.txt
gg_commit-0.0.1.dist-info/metadata.json
gg_commit-0.0.1.dist-info/top_level.txt
