Metadata-Version: 2.0
Name: gg-commit
Version: 0.0.1
Summary: Plugin for gg for committing branches
Home-page: https://github.com/peterbe/gg-commit
Author: Peter Bengtsson
Author-email: mail@peterbe.com
License: MIT
Platform: UNKNOWN
Requires-Dist: gg
